{
  "发票类型": "电子发票(普通发票)",
  "发票号码": "24932000000070744246",
  "开票日期": "2024年09月19日",
  "购买方名称": "同济大学",
  "购买方税号": "12100000425006125J",
  "销售方名称": "宁波紫辰信息科技有限公司",
  "销售方税号": "91330211MA2J4BLX3H",
  "项目明细": [
    {
      "项目名称": "*计算机外部设备*固态硬盘",
      "规格型号": "",
      "单位": "个",
      "数量": "1",
      "单价": "884.070796460177",
      "金额": "884.07",
      "税率": "13%",
      "税额": "114.93"
    }
  ],
  "价税合计大写": "玖佰玖拾玖圆整",
  "价税合计小写": "¥999.00",
  "备注": "",
  "开票人": "",
  "二维码内容": "",
  "文件路径": "invoice_samples_standard/invoice_file_05.pdf",
  "处理时间": "2025-06-13 23:49:13",
  "文件MD5": "2154920884d58d88e79caf021f55046f"
}